bbobtorch/Problem.py
bbobtorch/__init__.py
bbobtorch/functions.py
bbobtorch/utils.py
BBOBtorch-1.0.1.dist-info/LICENSE.md
BBOBtorch-1.0.1.dist-info/METADATA
BBOBtorch-1.0.1.dist-info/WHEEL
BBOBtorch-1.0.1.dist-info/top_level.txt
BBOBtorch-1.0.1.dist-info/RECORD
