Metadata-Version: 2.1
Name: BBOBtorch
Version: 1.0.1
Summary: Vectorized BBOB functions in torch
Home-page: https://github.com/PatrikValkovic/BBOBtorch
Author: Patrik Valkovic
License: MIT
Download-URL: https://github.com/PatrikValkovic/BBOBtorch/archive/v1.0.1.tar.gz
Platform: UNKNOWN
Requires-Dist: torch
